skill_holidays/LICENSE.md
skill_holidays/README.md
skill_holidays/__init__.py
skill_holidays/holidays.json
skill_holidays/skill.json
skill_holidays/version.py
skill_holidays/locale/en-us/dialog/holiday_date.dialog
skill_holidays/locale/en-us/dialog/no_holiday_on_date.dialog
skill_holidays/locale/en-us/intent/holiday_on_date.intent
skill_holidays/locale/en-us/vocab/when.voc
skill_holidays/neon_skill_holidays.egg-info/PKG-INFO
skill_holidays/neon_skill_holidays.egg-info/SOURCES.txt
skill_holidays/neon_skill_holidays.egg-info/dependency_links.txt
skill_holidays/neon_skill_holidays.egg-info/entry_points.txt
skill_holidays/neon_skill_holidays.egg-info/requires.txt
skill_holidays/neon_skill_holidays.egg-info/top_level.txt
skill_holidays/test/test_skill.py
neon_skill_holidays-0.0.0a1.dist-info/LICENSE.md
neon_skill_holidays-0.0.0a1.dist-info/METADATA
neon_skill_holidays-0.0.0a1.dist-info/WHEEL
neon_skill_holidays-0.0.0a1.dist-info/entry_points.txt
neon_skill_holidays-0.0.0a1.dist-info/top_level.txt
neon_skill_holidays-0.0.0a1.dist-info/RECORD
