Metadata-Version: 2.1
Name: neon-skill-holidays
Version: 0.0.0a1
Home-page: https://github.com/NeonGeckoCom/skill-holidays
Author: Neongecko
Author-email: developers@neon.ai
License: BSD-3-Clause
License-File: LICENSE.md
Requires-Dist: ovos-workshop (>=0.0.12a4,~=0.0.11)
Requires-Dist: ovos-lingua-franca (>=0.4.6,~=0.4)
Requires-Dist: requests (~=2.0)
